arxivterminal/__init__.py
arxivterminal/cli.py
arxivterminal/constants.py
arxivterminal/db.py
arxivterminal/download.py
arxivterminal/fetch.py
arxivterminal/ml.py
arxivterminal/models.py
arxivterminal/output.py
arxivterminal-0.3.1.dist-info/LICENSE
arxivterminal-0.3.1.dist-info/METADATA
arxivterminal-0.3.1.dist-info/WHEEL
arxivterminal-0.3.1.dist-info/entry_points.txt
arxivterminal-0.3.1.dist-info/RECORD
