Metadata-Version: 2.1
Name: arxivterminal
Version: 0.3.1
Summary: An application for summarizing Arxiv results within the terminal
Home-page: https://github.com/jbencina/arxivterminal
License: GPL-3.0-or-later
Keywords: arxiv
Author: John Bencina
Author-email: jbencina@users.noreply.github.com
Requires-Python: >=3.9,<4.0
Classifier: License :: OSI Approved :: GNU General Public License v3 or later (GPLv3+)
Classifier: Programming Language :: Python :: 3
Classifier: Programming Language :: Python :: 3.9
Classifier: Programming Language :: Python :: 3.10
Classifier: Programming Language :: Python :: 3.11
Requires-Dist: appdirs (>=1.4.4,<2.0.0)
Requires-Dist: arxiv (>=1.4.3,<2.0.0)
Requires-Dist: click (>=8.1.3,<9.0.0)
Requires-Dist: pydantic (>=1.10.7,<2.0.0)
Requires-Dist: scikit-learn (>=1.2.2,<2.0.0)
Requires-Dist: termcolor (>=2.2.0,<3.0.0)
Project-URL: Repository, https://github.com/jbencina/arxivterminal
